drf_signed_auth/__init__.py
drf_signed_auth/authentication.py
drf_signed_auth/compat.py
drf_signed_auth/settings.py
drf_signed_auth/signing.py
drf_signed_auth/views.py
drf_signed_auth/__pycache__/__init__.cpython-36.pyc
drf_signed_auth/__pycache__/authentication.cpython-36.pyc
drf_signed_auth/__pycache__/compat.cpython-36.pyc
drf_signed_auth/__pycache__/settings.cpython-36.pyc
drf_signed_auth/__pycache__/signing.cpython-36.pyc
drf_signed_auth/__pycache__/views.cpython-36.pyc
drf_signed_auth-0.1.1.dist-info/DESCRIPTION.rst
drf_signed_auth-0.1.1.dist-info/METADATA
drf_signed_auth-0.1.1.dist-info/RECORD
drf_signed_auth-0.1.1.dist-info/WHEEL
drf_signed_auth-0.1.1.dist-info/metadata.json
drf_signed_auth-0.1.1.dist-info/top_level.txt
